<annotation>
<filename>0279.jpg</filename>
<size>
<width>624</width>
<height>352</height>
</size>
<object>
<name>person</name>
<bndbox>
<xmin>402</xmin>
<ymin>116</ymin>
<xmax>469</xmax>
<ymax>226</ymax>
</bndbox>
</object><object>
<name>person</name>
<bndbox>
<xmin>399</xmin>
<ymin>116</ymin>
<xmax>466</xmax>
<ymax>226</ymax>
</bndbox>
</object><object>
<name>person</name>
<bndbox>
<xmin>405</xmin>
<ymin>116</ymin>
<xmax>472</xmax>
<ymax>226</ymax>
</bndbox>
</object><object>
<name>person</name>
<bndbox>
<xmin>402</xmin>
<ymin>113</ymin>
<xmax>469</xmax>
<ymax>223</ymax>
</bndbox>
</object><object>
<name>person</name>
<bndbox>
<xmin>402</xmin>
<ymin>119</ymin>
<xmax>469</xmax>
<ymax>229</ymax>
</bndbox>
</object></annotation>