<annotation>
<filename>0411.jpg</filename>
<size>
<width>576</width>
<height>432</height>
</size>
<object>
<name>person</name>
<bndbox>
<xmin>160</xmin>
<ymin>234</ymin>
<xmax>194</xmax>
<ymax>315</ymax>
</bndbox>
</object><object>
<name>person</name>
<bndbox>
<xmin>159</xmin>
<ymin>234</ymin>
<xmax>193</xmax>
<ymax>315</ymax>
</bndbox>
</object><object>
<name>person</name>
<bndbox>
<xmin>161</xmin>
<ymin>234</ymin>
<xmax>195</xmax>
<ymax>315</ymax>
</bndbox>
</object><object>
<name>person</name>
<bndbox>
<xmin>160</xmin>
<ymin>233</ymin>
<xmax>194</xmax>
<ymax>314</ymax>
</bndbox>
</object><object>
<name>person</name>
<bndbox>
<xmin>160</xmin>
<ymin>235</ymin>
<xmax>194</xmax>
<ymax>316</ymax>
</bndbox>
</object></annotation>