<annotation>
<filename>0631.jpg</filename>
<size>
<width>576</width>
<height>432</height>
</size>
<object>
<name>person</name>
<bndbox>
<xmin>330</xmin>
<ymin>146</ymin>
<xmax>364</xmax>
<ymax>227</ymax>
</bndbox>
</object><object>
<name>person</name>
<bndbox>
<xmin>329</xmin>
<ymin>146</ymin>
<xmax>363</xmax>
<ymax>227</ymax>
</bndbox>
</object><object>
<name>person</name>
<bndbox>
<xmin>331</xmin>
<ymin>146</ymin>
<xmax>365</xmax>
<ymax>227</ymax>
</bndbox>
</object><object>
<name>person</name>
<bndbox>
<xmin>330</xmin>
<ymin>145</ymin>
<xmax>364</xmax>
<ymax>226</ymax>
</bndbox>
</object><object>
<name>person</name>
<bndbox>
<xmin>330</xmin>
<ymin>147</ymin>
<xmax>364</xmax>
<ymax>228</ymax>
</bndbox>
</object></annotation>