<annotation>
<filename>0283.jpg</filename>
<size>
<width>576</width>
<height>432</height>
</size>
<object>
<name>person</name>
<bndbox>
<xmin>191</xmin>
<ymin>193</ymin>
<xmax>225</xmax>
<ymax>274</ymax>
</bndbox>
</object><object>
<name>person</name>
<bndbox>
<xmin>190</xmin>
<ymin>193</ymin>
<xmax>224</xmax>
<ymax>274</ymax>
</bndbox>
</object><object>
<name>person</name>
<bndbox>
<xmin>192</xmin>
<ymin>193</ymin>
<xmax>226</xmax>
<ymax>274</ymax>
</bndbox>
</object><object>
<name>person</name>
<bndbox>
<xmin>191</xmin>
<ymin>192</ymin>
<xmax>225</xmax>
<ymax>273</ymax>
</bndbox>
</object><object>
<name>person</name>
<bndbox>
<xmin>191</xmin>
<ymin>194</ymin>
<xmax>225</xmax>
<ymax>275</ymax>
</bndbox>
</object><object>
<name>target_negative</name>
<bndbox>
<xmin>495</xmin>
<ymin>259</ymin>
<xmax>574</xmax>
<ymax>423</ymax>
</bndbox>
</object><object>
<name>target_negative</name>
<bndbox>
<xmin>257</xmin>
<ymin>102</ymin>
<xmax>314</xmax>
<ymax>343</ymax>
</bndbox>
</object><object>
<name>target_negative</name>
<bndbox>
<xmin>147</xmin>
<ymin>389</ymin>
<xmax>508</xmax>
<ymax>399</ymax>
</bndbox>
</object><object>
<name>target_negative</name>
<bndbox>
<xmin>531</xmin>
<ymin>399</ymin>
<xmax>562</xmax>
<ymax>411</ymax>
</bndbox>
</object><object>
<name>target_negative</name>
<bndbox>
<xmin>451</xmin>
<ymin>144</ymin>
<xmax>544</xmax>
<ymax>252</ymax>
</bndbox>
</object><object>
<name>target_negative</name>
<bndbox>
<xmin>434</xmin>
<ymin>377</ymin>
<xmax>545</xmax>
<ymax>402</ymax>
</bndbox>
</object></annotation>