<annotation>
<filename>0168.jpg</filename>
<size>
<width>624</width>
<height>352</height>
</size>
<object>
<name>person</name>
<bndbox>
<xmin>354</xmin>
<ymin>144</ymin>
<xmax>422</xmax>
<ymax>252</ymax>
</bndbox>
</object><object>
<name>person</name>
<bndbox>
<xmin>351</xmin>
<ymin>144</ymin>
<xmax>419</xmax>
<ymax>252</ymax>
</bndbox>
</object><object>
<name>person</name>
<bndbox>
<xmin>357</xmin>
<ymin>144</ymin>
<xmax>425</xmax>
<ymax>252</ymax>
</bndbox>
</object><object>
<name>person</name>
<bndbox>
<xmin>354</xmin>
<ymin>141</ymin>
<xmax>422</xmax>
<ymax>249</ymax>
</bndbox>
</object><object>
<name>person</name>
<bndbox>
<xmin>354</xmin>
<ymin>147</ymin>
<xmax>422</xmax>
<ymax>255</ymax>
</bndbox>
</object><object>
<name>target_negative</name>
<bndbox>
<xmin>113</xmin>
<ymin>313</ymin>
<xmax>557</xmax>
<ymax>322</ymax>
</bndbox>
</object><object>
<name>target_negative</name>
<bndbox>
<xmin>337</xmin>
<ymin>252</ymin>
<xmax>459</xmax>
<ymax>305</ymax>
</bndbox>
</object><object>
<name>target_negative</name>
<bndbox>
<xmin>206</xmin>
<ymin>227</ymin>
<xmax>258</xmax>
<ymax>327</ymax>
</bndbox>
</object><object>
<name>target_negative</name>
<bndbox>
<xmin>145</xmin>
<ymin>274</ymin>
<xmax>241</xmax>
<ymax>309</ymax>
</bndbox>
</object><object>
<name>target_negative</name>
<bndbox>
<xmin>219</xmin>
<ymin>215</ymin>
<xmax>320</xmax>
<ymax>251</ymax>
</bndbox>
</object><object>
<name>target_negative</name>
<bndbox>
<xmin>412</xmin>
<ymin>276</ymin>
<xmax>483</xmax>
<ymax>300</ymax>
</bndbox>
</object></annotation>