<annotation>
<filename>0352.jpg</filename>
<size>
<width>624</width>
<height>352</height>
</size>
<object>
<name>person</name>
<bndbox>
<xmin>290</xmin>
<ymin>72</ymin>
<xmax>374</xmax>
<ymax>236</ymax>
</bndbox>
</object><object>
<name>person</name>
<bndbox>
<xmin>287</xmin>
<ymin>72</ymin>
<xmax>371</xmax>
<ymax>236</ymax>
</bndbox>
</object><object>
<name>person</name>
<bndbox>
<xmin>293</xmin>
<ymin>72</ymin>
<xmax>377</xmax>
<ymax>236</ymax>
</bndbox>
</object><object>
<name>person</name>
<bndbox>
<xmin>290</xmin>
<ymin>69</ymin>
<xmax>374</xmax>
<ymax>233</ymax>
</bndbox>
</object><object>
<name>person</name>
<bndbox>
<xmin>290</xmin>
<ymin>75</ymin>
<xmax>374</xmax>
<ymax>239</ymax>
</bndbox>
</object><object>
<name>target_negative</name>
<bndbox>
<xmin>547</xmin>
<ymin>244</ymin>
<xmax>624</xmax>
<ymax>289</ymax>
</bndbox>
</object><object>
<name>target_negative</name>
<bndbox>
<xmin>164</xmin>
<ymin>103</ymin>
<xmax>423</xmax>
<ymax>226</ymax>
</bndbox>
</object><object>
<name>target_negative</name>
<bndbox>
<xmin>119</xmin>
<ymin>334</ymin>
<xmax>398</xmax>
<ymax>334</ymax>
</bndbox>
</object><object>
<name>target_negative</name>
<bndbox>
<xmin>468</xmin>
<ymin>230</ymin>
<xmax>555</xmax>
<ymax>348</ymax>
</bndbox>
</object><object>
<name>target_negative</name>
<bndbox>
<xmin>577</xmin>
<ymin>159</ymin>
<xmax>595</xmax>
<ymax>178</ymax>
</bndbox>
</object><object>
<name>target_negative</name>
<bndbox>
<xmin>401</xmin>
<ymin>235</ymin>
<xmax>409</xmax>
<ymax>309</ymax>
</bndbox>
</object></annotation>